<?xml version="1.0" encoding="UTF-8"?>
<export version="D">
  <design>
    <source>/Users/rclott/root/files/projs/novac/eda/tracer/tracer.sch</source>
    <date>2021 June 15, Tuesday 13:13:06</date>
    <tool>Eeschema (5.1.9-0-10_14)</tool>
    <sheet number="1" name="/" tstamps="/">
      <title_block>
        <title>The TraceR</title>
        <company/>
        <rev/>
        <date>2021-05-17</date>
        <source>tracer.sch</source>
        <comment number="1" value=""/>
        <comment number="2" value=""/>
        <comment number="3" value=""/>
        <comment number="4" value=""/>
      </title_block>
    </sheet>
  </design>
  <components>
    <comp ref="K1">
      <value>Coto-9913-05-20</value>
      <footprint>.tracer:REED_RELAY_COTO_9913</footprint>
      <libsource lib=".tracer" part="COTO-9913-REED-RELAY" description=""/>
      <sheetpath names="/" tstamps="/"/>
      <tstamp>6093F5CC</tstamp>
    </comp>
    <comp ref="U1">
      <value>AD8403ARZ1</value>
      <footprint>.tracer:SOIC-24W_7.5x15.4mm_P1.27mm</footprint>
      <libsource lib=".tracer" part="AD8403ARZ1" description=""/>
      <sheetpath names="/" tstamps="/"/>
      <tstamp>609402F4</tstamp>
    </comp>
    <comp ref="A1">
      <value>Tiny2040</value>
      <footprint>.tracer:MODULE_TINY_2040_DEV2</footprint>
      <libsource lib=".tracer" part="Tiny2040" description=""/>
      <sheetpath names="/" tstamps="/"/>
      <tstamp>60983233</tstamp>
    </comp>
    <comp ref="U2">
      <value>AD8403ARZ1</value>
      <footprint>.tracer:SOIC-24W_7.5x15.4mm_P1.27mm</footprint>
      <libsource lib=".tracer" part="AD8403ARZ1" description=""/>
      <sheetpath names="/" tstamps="/"/>
      <tstamp>60AF4B09</tstamp>
    </comp>
    <comp ref="K2">
      <value>Coto-9913-05-20</value>
      <footprint>.tracer:REED_RELAY_COTO_9913</footprint>
      <libsource lib=".tracer" part="COTO-9913-REED-RELAY" description=""/>
      <sheetpath names="/" tstamps="/"/>
      <tstamp>60AF646A</tstamp>
    </comp>
    <comp ref="Q2">
      <value>MMBT3904</value>
      <footprint>.tracer:SOT-23</footprint>
      <datasheet>https://www.onsemi.com/pub/Collateral/2N3903-D.PDF</datasheet>
      <libsource lib=".tracer" part="MMBT3904" description=""/>
      <sheetpath names="/" tstamps="/"/>
      <tstamp>60AB9105</tstamp>
    </comp>
    <comp ref="R2">
      <value>1K</value>
      <footprint>.tracer:R_0805_2012Metric</footprint>
      <libsource lib=".tracer" part="R_US" description=""/>
      <sheetpath names="/" tstamps="/"/>
      <tstamp>60ABAE1C</tstamp>
    </comp>
    <comp ref="Q1">
      <value>MMBT3904</value>
      <footprint>.tracer:SOT-23</footprint>
      <datasheet>https://www.onsemi.com/pub/Collateral/2N3903-D.PDF</datasheet>
      <libsource lib=".tracer" part="MMBT3904" description=""/>
      <sheetpath names="/" tstamps="/"/>
      <tstamp>60ADC9F4</tstamp>
    </comp>
    <comp ref="R1">
      <value>1K</value>
      <footprint>.tracer:R_0805_2012Metric</footprint>
      <libsource lib=".tracer" part="R_US" description=""/>
      <sheetpath names="/" tstamps="/"/>
      <tstamp>60ADC9FE</tstamp>
    </comp>
    <comp ref="A2">
      <value>ASSY_OLED_490MILS_62x32_I2C</value>
      <footprint>.tracer:MODULE_OLED_490_SMALL_PADS</footprint>
      <libsource lib=".tracer" part="ASSY_OLED_490MILS_62x32_I2C" description=""/>
      <sheetpath names="/" tstamps="/"/>
      <tstamp>60B700C9</tstamp>
    </comp>
    <comp ref="J1">
      <value>IO_JACK_F04_SPLIT</value>
      <footprint>.tracer:SAMTEC-SSQ-102-02-SIDEWAYS</footprint>
      <libsource lib=".tracer" part="IO_JACK_F04_SPLIT" description=""/>
      <sheetpath names="/" tstamps="/"/>
      <tstamp>609A8705</tstamp>
    </comp>
    <comp ref="D2">
      <value>1N4148W</value>
      <footprint>.tracer:DFN1006-2</footprint>
      <libsource lib=".tracer" part="DIODE" description=""/>
      <sheetpath names="/" tstamps="/"/>
      <tstamp>60A62D2E</tstamp>
    </comp>
    <comp ref="D1">
      <value>1N4148W</value>
      <footprint>.tracer:DFN1006-2</footprint>
      <libsource lib=".tracer" part="DIODE" description=""/>
      <sheetpath names="/" tstamps="/"/>
      <tstamp>60A7F081</tstamp>
    </comp>
    <comp ref="LOGO1">
      <value>Logo_Open_Hardware_Small</value>
      <footprint>.tracer:OSHW-Logo2_7.3x6mm_SilkScreen</footprint>
      <datasheet>~</datasheet>
      <libsource lib=".tracer" part="Logo_Open_Hardware_Small" description=""/>
      <sheetpath names="/" tstamps="/"/>
      <tstamp>60A81A58</tstamp>
    </comp>
    <comp ref="U3">
      <value>TXS0101</value>
      <footprint>.tracer:SOT-23-6</footprint>
      <libsource lib=".tracer" part="TXS0101" description=""/>
      <sheetpath names="/" tstamps="/"/>
      <tstamp>60ABC084</tstamp>
    </comp>
    <comp ref="R3">
      <value>1K</value>
      <footprint>.tracer:R_0805_2012Metric</footprint>
      <libsource lib=".tracer" part="R_US" description=""/>
      <sheetpath names="/" tstamps="/"/>
      <tstamp>60C5D365</tstamp>
    </comp>
    <comp ref="R4">
      <value>1K</value>
      <footprint>.tracer:R_0805_2012Metric</footprint>
      <libsource lib=".tracer" part="R_US" description=""/>
      <sheetpath names="/" tstamps="/"/>
      <tstamp>60C690E0</tstamp>
    </comp>
    <comp ref="S1">
      <value>B3U-3100P-B</value>
      <footprint>.tracer:SW_B3U-3100P-B</footprint>
      <fields>
        <field name="MANUFACTURER">Omron</field>
      </fields>
      <libsource lib=".tracer" part="B3U-3100P-B" description=""/>
      <sheetpath names="/" tstamps="/"/>
      <tstamp>60E5A35A</tstamp>
    </comp>
    <comp ref="S2">
      <value>B3U-3100P-B</value>
      <footprint>.tracer:SW_B3U-3100P-B</footprint>
      <fields>
        <field name="MANUFACTURER">Omron</field>
      </fields>
      <libsource lib=".tracer" part="B3U-3100P-B" description=""/>
      <sheetpath names="/" tstamps="/"/>
      <tstamp>60E5AFAD</tstamp>
    </comp>
  </components>
  <libparts>
    <libpart lib=".tracer" part="AD8403ARZ10">
      <aliases>
        <alias>AD8403ARZ1</alias>
        <alias>AD8403ARZ100</alias>
      </aliases>
      <fields>
        <field name="Reference">U</field>
        <field name="Value">AD8403ARZ10</field>
      </fields>
      <pins>
        <pin num="1" name="AGND2" type="passive"/>
        <pin num="2" name="B2" type="passive"/>
        <pin num="3" name="A2" type="passive"/>
        <pin num="4" name="W2" type="passive"/>
        <pin num="5" name="AGND4" type="passive"/>
        <pin num="6" name="B4" type="passive"/>
        <pin num="7" name="A4" type="passive"/>
        <pin num="8" name="W4" type="passive"/>
        <pin num="9" name="DGND" type="passive"/>
        <pin num="10" name="~SHDN" type="input"/>
        <pin num="11" name="~CS" type="input"/>
        <pin num="12" name="SDI" type="input"/>
        <pin num="13" name="SDO" type="output"/>
        <pin num="14" name="CLK" type="input"/>
        <pin num="15" name="~RS" type="input"/>
        <pin num="16" name="VDD" type="power_in"/>
        <pin num="17" name="AGND3" type="passive"/>
        <pin num="18" name="W3" type="passive"/>
        <pin num="19" name="A3" type="passive"/>
        <pin num="20" name="B3" type="passive"/>
        <pin num="21" name="AGND1" type="passive"/>
        <pin num="22" name="W1" type="passive"/>
        <pin num="23" name="A1" type="passive"/>
        <pin num="24" name="B1" type="passive"/>
      </pins>
    </libpart>
    <libpart lib=".tracer" part="ASSY_OLED_490MILS_62x32_I2C">
      <fields>
        <field name="Reference">A</field>
        <field name="Value">ASSY_OLED_490MILS_62x32_I2C</field>
      </fields>
      <pins>
        <pin num="1" name="GND" type="passive"/>
        <pin num="2" name="VCC" type="passive"/>
        <pin num="3" name="SCL" type="passive"/>
        <pin num="4" name="SDA" type="passive"/>
      </pins>
    </libpart>
    <libpart lib=".tracer" part="B3U-3100P-B">
      <fields>
        <field name="Reference">S</field>
        <field name="Value">B3U-3100P-B</field>
        <field name="Footprint">SW_B3U-3100P-B</field>
        <field name="MANUFACTURER">Omron</field>
      </fields>
      <pins>
        <pin num="1" name="1" type="passive"/>
        <pin num="2" name="2" type="passive"/>
        <pin num="3" name="3" type="passive"/>
      </pins>
    </libpart>
    <libpart lib=".tracer" part="BC817">
      <aliases>
        <alias>BC818</alias>
        <alias>BC846</alias>
        <alias>BC847</alias>
        <alias>BC848</alias>
        <alias>BC849</alias>
        <alias>BC850</alias>
        <alias>MMBT3904</alias>
        <alias>MMBT5550L</alias>
        <alias>MMBT5551L</alias>
      </aliases>
      <footprints>
        <fp>SOT?23*</fp>
      </footprints>
      <fields>
        <field name="Reference">Q</field>
        <field name="Value">BC817</field>
        <field name="Footprint">Package_TO_SOT_SMD:SOT-23</field>
      </fields>
      <pins>
        <pin num="1" name="B" type="input"/>
        <pin num="2" name="E" type="passive"/>
        <pin num="3" name="C" type="passive"/>
      </pins>
    </libpart>
    <libpart lib=".tracer" part="COTO-9913-REED-RELAY">
      <fields>
        <field name="Reference">K</field>
        <field name="Value">COTO-9913-REED-RELAY</field>
      </fields>
      <pins>
        <pin num="1" name="~" type="passive"/>
        <pin num="2" name="~" type="passive"/>
        <pin num="3" name="~" type="passive"/>
        <pin num="4" name="~" type="passive"/>
      </pins>
    </libpart>
    <libpart lib=".tracer" part="DIODE">
      <footprints>
        <fp>TO-???*</fp>
        <fp>*_Diode_*</fp>
        <fp>*SingleDiode*</fp>
        <fp>D_*</fp>
      </footprints>
      <fields>
        <field name="Reference">D</field>
        <field name="Value">DIODE</field>
      </fields>
      <pins>
        <pin num="1" name="K" type="passive"/>
        <pin num="2" name="A" type="passive"/>
      </pins>
    </libpart>
    <libpart lib=".tracer" part="IO_JACK_F04_SPLIT">
      <footprints>
        <fp>Connector*:*_1x??_*</fp>
      </footprints>
      <fields>
        <field name="Reference">J</field>
        <field name="Value">IO_JACK_F04_SPLIT</field>
      </fields>
      <pins>
        <pin num="1" name="Pin_1" type="passive"/>
        <pin num="2" name="Pin_2" type="passive"/>
        <pin num="3" name="Pin_3" type="passive"/>
        <pin num="4" name="Pin_4" type="passive"/>
      </pins>
    </libpart>
    <libpart lib=".tracer" part="Logo_Open_Hardware_Small">
      <fields>
        <field name="Reference">#LOGO</field>
        <field name="Value">Logo_Open_Hardware_Small</field>
      </fields>
    </libpart>
    <libpart lib=".tracer" part="R_US">
      <footprints>
        <fp>R_*</fp>
      </footprints>
      <fields>
        <field name="Reference">R</field>
        <field name="Value">R_US</field>
      </fields>
      <pins>
        <pin num="1" name="~" type="passive"/>
        <pin num="2" name="~" type="passive"/>
      </pins>
    </libpart>
    <libpart lib=".tracer" part="TXS0101">
      <footprints>
        <fp>SOT?23*</fp>
      </footprints>
      <fields>
        <field name="Reference">U</field>
        <field name="Value">TXS0101</field>
      </fields>
      <pins>
        <pin num="1" name="VCCA" type="power_in"/>
        <pin num="2" name="GND" type="power_in"/>
        <pin num="3" name="A" type="BiDi"/>
        <pin num="4" name="B" type="BiDi"/>
        <pin num="5" name="OE" type="input"/>
        <pin num="6" name="VCCB" type="power_in"/>
      </pins>
    </libpart>
    <libpart lib=".tracer" part="Tiny2040">
      <fields>
        <field name="Reference">U</field>
        <field name="Value">Tiny2040</field>
      </fields>
      <pins>
        <pin num="1" name="VBUS" type="passive"/>
        <pin num="2" name="GND" type="passive"/>
        <pin num="3" name="3V3" type="passive"/>
        <pin num="4" name="GP29" type="passive"/>
        <pin num="5" name="GP28" type="passive"/>
        <pin num="6" name="GP27" type="passive"/>
        <pin num="7" name="GP26" type="passive"/>
        <pin num="8" name="GND" type="passive"/>
        <pin num="9" name="GP7" type="passive"/>
        <pin num="10" name="GP6" type="passive"/>
        <pin num="11" name="GP5" type="passive"/>
        <pin num="12" name="GP4" type="passive"/>
        <pin num="13" name="GP3" type="passive"/>
        <pin num="14" name="GP2" type="passive"/>
        <pin num="15" name="GP1" type="passive"/>
        <pin num="16" name="GP0" type="passive"/>
      </pins>
    </libpart>
  </libparts>
  <libraries>
    <library logical=".tracer">
      <uri>/Users/rclott/root/files/projs/novac/eda/tracer/tracer.lib</uri>
    </library>
  </libraries>
  <nets>
    <net code="1" name="GND">
      <node ref="U1" pin="1"/>
      <node ref="U1" pin="17"/>
      <node ref="U1" pin="21"/>
      <node ref="U1" pin="5"/>
      <node ref="U1" pin="9"/>
      <node ref="S2" pin="3"/>
      <node ref="A1" pin="2"/>
      <node ref="S2" pin="1"/>
      <node ref="S1" pin="3"/>
      <node ref="S1" pin="1"/>
      <node ref="A1" pin="8"/>
      <node ref="Q2" pin="2"/>
      <node ref="Q1" pin="2"/>
      <node ref="U2" pin="9"/>
      <node ref="A2" pin="1"/>
      <node ref="U2" pin="5"/>
      <node ref="U2" pin="21"/>
      <node ref="U2" pin="17"/>
      <node ref="U2" pin="1"/>
      <node ref="U3" pin="2"/>
    </net>
    <net code="2" name="Net-(A1-Pad15)">
      <node ref="A2" pin="3"/>
      <node ref="A1" pin="15"/>
    </net>
    <net code="3" name="+3V3">
      <node ref="A1" pin="3"/>
      <node ref="A2" pin="2"/>
      <node ref="U3" pin="1"/>
    </net>
    <net code="4" name="/SIG1B">
      <node ref="U1" pin="24"/>
      <node ref="U1" pin="2"/>
      <node ref="J1" pin="3"/>
      <node ref="U1" pin="20"/>
      <node ref="K1" pin="4"/>
      <node ref="U1" pin="6"/>
    </net>
    <net code="5" name="/SIG1A">
      <node ref="J1" pin="1"/>
      <node ref="U1" pin="8"/>
      <node ref="U1" pin="7"/>
      <node ref="U1" pin="4"/>
      <node ref="U1" pin="3"/>
      <node ref="U1" pin="23"/>
      <node ref="U1" pin="22"/>
      <node ref="U1" pin="19"/>
      <node ref="U1" pin="18"/>
      <node ref="K1" pin="3"/>
    </net>
    <net code="6" name="+5V">
      <node ref="K1" pin="1"/>
      <node ref="U2" pin="16"/>
      <node ref="K2" pin="1"/>
      <node ref="D2" pin="1"/>
      <node ref="D1" pin="1"/>
      <node ref="U3" pin="6"/>
      <node ref="R3" pin="2"/>
      <node ref="R4" pin="2"/>
      <node ref="U1" pin="16"/>
      <node ref="A1" pin="1"/>
    </net>
    <net code="7" name="/~RS">
      <node ref="U1" pin="15"/>
      <node ref="A1" pin="7"/>
      <node ref="U2" pin="15"/>
    </net>
    <net code="8" name="/SIG2A">
      <node ref="U2" pin="3"/>
      <node ref="U2" pin="22"/>
      <node ref="U2" pin="4"/>
      <node ref="U2" pin="7"/>
      <node ref="U2" pin="19"/>
      <node ref="U2" pin="18"/>
      <node ref="J1" pin="2"/>
      <node ref="U2" pin="8"/>
      <node ref="K2" pin="3"/>
      <node ref="U2" pin="23"/>
    </net>
    <net code="9" name="/SIG2B">
      <node ref="U2" pin="24"/>
      <node ref="U2" pin="6"/>
      <node ref="U2" pin="20"/>
      <node ref="U2" pin="2"/>
      <node ref="K2" pin="4"/>
      <node ref="J1" pin="4"/>
    </net>
    <net code="10" name="/~SS">
      <node ref="U2" pin="11"/>
      <node ref="A1" pin="11"/>
      <node ref="U1" pin="11"/>
    </net>
    <net code="11" name="/CLK">
      <node ref="U1" pin="14"/>
      <node ref="A1" pin="10"/>
      <node ref="U2" pin="14"/>
    </net>
    <net code="12" name="/SDI">
      <node ref="A1" pin="9"/>
      <node ref="U2" pin="12"/>
    </net>
    <net code="13" name="/RELAY1">
      <node ref="A1" pin="4"/>
      <node ref="R1" pin="2"/>
    </net>
    <net code="14" name="Net-(Q2-Pad1)">
      <node ref="R2" pin="1"/>
      <node ref="Q2" pin="1"/>
    </net>
    <net code="15" name="/RELAY2">
      <node ref="A1" pin="5"/>
      <node ref="R2" pin="2"/>
    </net>
    <net code="16" name="Net-(Q1-Pad1)">
      <node ref="R1" pin="1"/>
      <node ref="Q1" pin="1"/>
    </net>
    <net code="17" name="Net-(A1-Pad16)">
      <node ref="A2" pin="4"/>
      <node ref="A1" pin="16"/>
    </net>
    <net code="18" name="Net-(D2-Pad2)">
      <node ref="K2" pin="2"/>
      <node ref="Q2" pin="3"/>
      <node ref="D2" pin="2"/>
    </net>
    <net code="19" name="Net-(D1-Pad2)">
      <node ref="Q1" pin="3"/>
      <node ref="K1" pin="2"/>
      <node ref="D1" pin="2"/>
    </net>
    <net code="20" name="/SDO1_3V">
      <node ref="A1" pin="12"/>
      <node ref="U3" pin="3"/>
    </net>
    <net code="21" name="/~SHDN">
      <node ref="U1" pin="10"/>
      <node ref="U2" pin="10"/>
      <node ref="U3" pin="5"/>
      <node ref="A1" pin="6"/>
    </net>
    <net code="22" name="/SDO1_5V">
      <node ref="U3" pin="4"/>
      <node ref="R3" pin="1"/>
      <node ref="U1" pin="13"/>
    </net>
    <net code="23" name="/SDO2">
      <node ref="R4" pin="1"/>
      <node ref="U1" pin="12"/>
      <node ref="U2" pin="13"/>
    </net>
    <net code="24" name="Net-(A1-Pad13)">
      <node ref="A1" pin="13"/>
      <node ref="S1" pin="2"/>
    </net>
    <net code="25" name="Net-(A1-Pad14)">
      <node ref="S2" pin="2"/>
      <node ref="A1" pin="14"/>
    </net>
  </nets>
</export>
